LICENSE
MANIFEST.in
NOTICE
README.md
requirements.txt
setup.cfg
setup.py
compiler/__init__.py
compiler/api/__init__.py
compiler/api/compiler.py
compiler/api/source/auth_key.tl
compiler/api/source/main_api.tl
compiler/api/source/sys_msgs.tl
compiler/api/template/combinator.txt
compiler/api/template/type.txt
compiler/errors/__init__.py
compiler/errors/compiler.py
compiler/errors/sort.py
compiler/errors/source/303_SEE_OTHER.tsv
compiler/errors/source/400_BAD_REQUEST.tsv
compiler/errors/source/401_UNAUTHORIZED.tsv
compiler/errors/source/403_FORBIDDEN.tsv
compiler/errors/source/406_NOT_ACCEPTABLE.tsv
compiler/errors/source/420_FLOOD.tsv
compiler/errors/source/500_INTERNAL_SERVER_ERROR.tsv
compiler/errors/source/503_SERVICE_UNAVAILABLE.tsv
compiler/errors/template/class.txt
compiler/errors/template/sub_class.txt
geezram/__init__.py
geezram/geez/__init__.py
geezram/geez/database/__init__.py
geezram/geez/database/fitersdb.py
geezram/geez/database/gbandb.py
geezram/geez/database/global.py
geezram/geez/database/gmutedb.py
geezram/geez/database/notesdb.py
geezram/geez/database/pmpermit.py
geezram/geez/database/pmpermitdb.py
geezram/geez/database/sudodb.py
geezram/geez/helper/PyroHelpers.py
geezram/geez/helper/__init__.py
geezram/geez/helper/adminHelpers.py
geezram/geez/helper/aiohttp_helper.py
geezram/geez/helper/basic.py
geezram/geez/helper/constants.py
geezram/geez/helper/data.py
geezram/geez/helper/inline.py
geezram/geez/helper/interval.py
geezram/geez/helper/parser.py
geezram/geez/helper/pluginhelper.py
geezram/geez/helper/utility.py
geezram/geez/helper/what.py
geezram/geez/utils/__init__.py
geezram/geez/utils/misc.py
geezram/geez/utils/tools.py
geezram/ram/__init__.py
geezram/ram/helpers/PyroHelpers.py
geezram/ram/helpers/__init__.py
geezram/ram/helpers/adminHelpers.py
geezram/ram/helpers/basic.py
geezram/ram/helpers/constants.py
geezram/ram/helpers/data.py
geezram/ram/helpers/expand.py
geezram/ram/helpers/inline.py
geezram/ram/helpers/interval.py
geezramlibs.egg-info/PKG-INFO
geezramlibs.egg-info/SOURCES.txt
geezramlibs.egg-info/dependency_links.txt
geezramlibs.egg-info/not-zip-safe
geezramlibs.egg-info/requires.txt
geezramlibs.egg-info/top_level.txt
